asteroid_odyssey/__init__.py
asteroid_odyssey/api_client.py
asteroid_odyssey/api_response.py
asteroid_odyssey/configuration.py
asteroid_odyssey/exceptions.py
asteroid_odyssey/py.typed
asteroid_odyssey/rest.py
asteroid_odyssey/api/__init__.py
asteroid_odyssey/api/agent_profiles_api.py
asteroid_odyssey/api/agents_api.py
asteroid_odyssey/api/execution_api.py
asteroid_odyssey/api/files_api.py
asteroid_odyssey/models/__init__.py
asteroid_odyssey/models/agent_list200_response.py
asteroid_odyssey/models/agent_profile_clear_browser_cache200_response.py
asteroid_odyssey/models/agent_profiles_list200_response.py
asteroid_odyssey/models/agents_agent_base.py
asteroid_odyssey/models/agents_agent_execute_agent_request.py
asteroid_odyssey/models/agents_agent_execute_agent_response.py
asteroid_odyssey/models/agents_agent_sort_field.py
asteroid_odyssey/models/agents_execution_action_name.py
asteroid_odyssey/models/agents_execution_activity.py
asteroid_odyssey/models/agents_execution_activity_action_completed_info.py
asteroid_odyssey/models/agents_execution_activity_action_completed_payload.py
asteroid_odyssey/models/agents_execution_activity_action_failed_payload.py
asteroid_odyssey/models/agents_execution_activity_action_started_info.py
asteroid_odyssey/models/agents_execution_activity_action_started_payload.py
asteroid_odyssey/models/agents_execution_activity_continued_on_node_payload.py
asteroid_odyssey/models/agents_execution_activity_file_added_payload.py
asteroid_odyssey/models/agents_execution_activity_generic_payload.py
asteroid_odyssey/models/agents_execution_activity_payload_union.py
asteroid_odyssey/models/agents_execution_activity_playwright_script_generated_payload.py
asteroid_odyssey/models/agents_execution_activity_reasoning_payload.py
asteroid_odyssey/models/agents_execution_activity_status_changed_payload.py
asteroid_odyssey/models/agents_execution_activity_step_completed_payload.py
asteroid_odyssey/models/agents_execution_activity_step_started_payload.py
asteroid_odyssey-1.6.135.dist-info/METADATA
asteroid_odyssey-1.6.135.dist-info/WHEEL
asteroid_odyssey-1.6.135.dist-info/top_level.txt
asteroid_odyssey-1.6.135.dist-info/RECORD
